Metadata-Version: 2.4
Name: contextual-studio-ai-zerox
Version: 0.1.1
Summary: ocr documents using vision models from all popular providers like OpenAI, Azure OpenAI, Anthropic, AWS Bedrock etc
License: MIT
License-File: LICENSE
Keywords: ocr,document,llm
Author: wizenheimer
Requires-Python: >=3.11,<4.0
Classifier: License :: OSI Approved :: MIT License
Classifier: Programming Language :: Python :: 3
Classifier: Programming Language :: Python :: 3.11
Classifier: Programming Language :: Python :: 3.12
Classifier: Programming Language :: Python :: 3.13
Classifier: Programming Language :: Python :: 3.14
Requires-Dist: PyMuPDF (>=1.23.8,<2.0.0)
Requires-Dist: aiofiles (>=23.0,<24.0)
Requires-Dist: aiohttp (>=3.9.5,<4.0.0)
Requires-Dist: aioshutil (>=1.5,<2.0)
Requires-Dist: litellm (>=1.44.15,<2.0.0)
Requires-Dist: pypdf2 (>=3.0.1,<4.0.0)
Project-URL: Documentation, https://github.com/getomni-ai/zerox
Project-URL: Repository, https://github.com/getomni-ai/zerox.git
